accounts_pkg/__init__.py
accounts_pkg/api_urls.py
accounts_pkg/asgi.py
accounts_pkg/settings-multi-auth.py
accounts_pkg/settings.py
accounts_pkg/urls.py
accounts_pkg/wsgi.py
dj_accounts/__init__.py
dj_accounts/apps.py
dj_accounts/backends.py
dj_accounts/forms.py
dj_accounts/utils.py
dj_accounts/verify_phone.py
dj_accounts/views.py
dj_accounts/views_api.py
dj_accounts/locale/ar/LC_MESSAGES/django.mo
dj_accounts/locale/ar/LC_MESSAGES/django.po
dj_accounts/templates/dj_accounts/auth_base.html
dj_accounts/templates/dj_accounts/confirm_email_template.html
dj_accounts/templates/dj_accounts/email_verification_complete.html
dj_accounts/templates/dj_accounts/login.html
dj_accounts/templates/dj_accounts/password_reset_complete.html
dj_accounts/templates/dj_accounts/password_reset_confirm.html
dj_accounts/templates/dj_accounts/password_reset_done.html
dj_accounts/templates/dj_accounts/password_reset_email.html
dj_accounts/templates/dj_accounts/password_reset_form.html
dj_accounts/templates/dj_accounts/password_reset_subject.txt
dj_accounts/templates/dj_accounts/phone_verification_complete.html
dj_accounts/templates/dj_accounts/profile.html
dj_accounts/templates/dj_accounts/profile_base.html
dj_accounts/templates/dj_accounts/register.html
dj_accounts/templates/dj_accounts/sidebar.html
dj_accounts/templates/dj_accounts/update_email_form.html
dj_accounts/templates/dj_accounts/update_phone_number_form.html
dj_accounts/templates/dj_accounts/update_user_data_form.html
dj_accounts/templates/dj_accounts/update_user_password_form.html
dj_accounts/templates/dj_accounts/verify_phone.html
dj_accounts/templates/dj_accounts/partials/login-tabs.html
dj_accounts/templates/dj_accounts/partials/login_with_email.html
dj_accounts/templates/dj_accounts/partials/login_with_phone.html
dj_accounts/templates/dj_accounts/partials/logo.html
dj_accounts/templates/dj_accounts/partials/social_login.html
dj_accounts/templates/dj_accounts/partials/fields/birthdate.html
dj_accounts-4.1.0.dist-info/LICENSE
dj_accounts-4.1.0.dist-info/METADATA
dj_accounts-4.1.0.dist-info/WHEEL
dj_accounts-4.1.0.dist-info/top_level.txt
dj_accounts-4.1.0.dist-info/RECORD
